metatask/__init__.py
metatask/process.py
metatask/utils.py
metatask-1.0.2.dist-info/DESCRIPTION.rst
metatask-1.0.2.dist-info/METADATA
metatask-1.0.2.dist-info/RECORD
metatask-1.0.2.dist-info/WHEEL
metatask-1.0.2.dist-info/entry_points.txt
metatask-1.0.2.dist-info/metadata.json
metatask-1.0.2.dist-info/top_level.txt
