Metadata-Version: 2.0
Name: metatask
Version: 1.0.2
Summary: A tool and library to run task or moves on many files
Home-page: https://github.com/sbrunner/metatask/
Author: Stéphane Brunner
Author-email: stephane.brunner@gmail.com
License: UNKNOWN
Platform: UNKNOWN
Classifier: Programming Language :: Python :: 3
Requires-Dist: Jinja2
Requires-Dist: bashcolor
